[{"id": 1, "usec": 0, "x": -5.4176, "y": 0.6017, "z": 0.0}, {"id": 2, "usec": 0, "x": -4.3521, "y": -0.3378, "z": 0.15}, {"id": 3, "usec": 0, "x": -2.8089, "y": 2.1462, "z": 0.9}, {"id": 4, "usec": 0, "x": -3.6449, "y": -3.728, "z": 0.0}, {"id": 5, "usec": 0, "x": -6.0631, "y": 2.6602, "z": 0.0}, {"id": 6, "usec": 0, "x": -4.2556, "y": -5.1926, "z": 0.0}, {"id": 7, "usec": 0, "x": 3.6831, "y": 1.0445, "z": 0.0}, {"id": 8, "usec": 0, "x": 5.3541, "y": -0.2031, "z": 0.0}, {"id": 9, "usec": 0, "x": 3.9862, "y": 2.2101, "z": 0.0}, {"id": 10, "usec": 0, "x": 3.1732, "y": -4.0723, "z": 0.0}, {"id": 1, "usec": 1, "x": -6.7239, "y": 0.0201, "z": 0.0}, {"id": 2, "usec": 1, "x": -4.3123, "y": 1.9419, "z": 0.15}, {"id": 3, "usec": 1, "x": -2.9665, "y": 2.2694, "z": 1.16}, {"id": 4, "usec": 1, "x": -6.5792, "y": -5.5615, "z": 0.52}, {"id": 5, "usec": 1, "x": -6.0207, "y": 3.4691, "z": 0.0}, {"id": 6, "usec": 1, "x": -2.9449, "y": -6.1103, "z": 0.0}, {"id": 7, "usec": 1, "x": 3.0981, "y": 2.0578, "z": 0.0}, {"id": 8, "usec": 1, "x": 5.0751, "y": 1.0051, "z": 0.0}, {"id": 9, "usec": 1, "x": 5.3383, "y": 2.6757, "z": 0.01}, {"id": 10, "usec": 1, "x": 1.4643, "y": -0.8584, "z": 0.0}, {"id": 1, "usec": 2, "x": -4.0164, "y": 2.9236, "z": 0.0}, {"id": 2, "usec": 2, "x": -2.4667, "y": 2.4711, "z": 0.15}, {"id": 3, "usec": 2, "x": -2.7165, "y": 2.2694, "z": 1.16}, {"id": 4, "usec": 2, "x": -7.4136, "y": -6.3673, "z": 0.52}, {"id": 5, "usec": 2, "x": -7.8133, "y": 4.9732, "z": 0.0}, {"id": 6, "usec": 2, "x": -5.791, "y": -6.2595, "z": 0.14}, {"id": 7, "usec": 2, "x": 5.4802, "y": 2.3503, "z": 0.0}, {"id": 8, "usec": 2, "x": 1.3839, "y": 2.0636, "z": 0.0}, {"id": 9, "usec": 2, "x": 4.9414, "y": 4.0599, "z": 0.01}, {"id": 10, "usec": 2, "x": 3.7287, "y": 0.1028, "z": 0.41}, {"id": 1, "usec": 3, "x": -1.9334, "y": 0.3512, "z": 0.0}, {"id": 2, "usec": 3, "x": -3.0143, "y": 5.2884, "z": 0.15}, {"id": 3, "usec": 3, "x": -1.7777, "y": 1.0235, "z": 1.16}, {"id": 4, "usec": 3, "x": -7.6794, "y": -10.1681, "z": 0.52}, {"id": 5, "usec": 3, "x": -5.1758, "y": 7.6107, "z": 0.0}, {"id": 6, "usec": 3, "x": -4.0056, "y": -6.9093, "z": 0.14}, {"id": 7, "usec": 3, "x": 4.3839, "y": 2.1766, "z": 0.0}, {"id": 8, "usec": 3, "x": 1.0268, "y": 2.5206, "z": 0.0}, {"id": 9, "usec": 3, "x": 3.2144, "y": 3.8478, "z": 1.01}, {"id": 10, "usec": 3, "x": 1.2328, "y": 0.8659, "z": 0.41}, {"id": 1, "usec": 4, "x": -1.1763, "y": 2.6813, "z": 0.0}, {"id": 2, "usec": 4, "x": -3.7428, "y": 3.2868, "z": 0.15}, {"id": 3, "usec": 4, "x": -1.6948, "y": 1.547, "z": 1.16}, {"id": 4, "usec": 4, "x": -9.0637, "y": -8.5756, "z": 0.52}, {"id": 5, "usec": 4, "x": -2.6773, "y": 7.5235, "z": 0.0}, {"id": 6, "usec": 4, "x": -5.9508, "y": -6.2013, "z": 0.14}, {"id": 7, "usec": 4, "x": 1.4604, "y": -0.1075, "z": 0.0}, {"id": 8, "usec": 4, "x": 3.7792, "y": 4.3772, "z": 0.0}, {"id": 9, "usec": 4, "x": 3.8151, "y": 3.7419, "z": 1.01}, {"id": 10, "usec": 4, "x": 1.4134, "y": -1.7178, "z": 0.41}]